{"d":[{"PartitionKey":"7ada687c-639b-461c-b749-085717aa19ed","RowKey":"26270e97-b33f-486c-844f-4ea89d799d83","nitparroquias":"800044533-5","nombreparroquialesia":"CATEDRAL DEL SAGRADO CORAZÓN","direccionparroquiaiglesia":"CARRERA 8 No 16 - 28","barrio":"DAVID GUARIN","numerodetelefono_iglesia_parroquia":"7262214","correoiglesiaparroquia":"curia@diocesisdechiquinquira.org","comunidad":"DIOCESANA","patrono":"SAGRADO CORAZÓN DE JESÚS","fechafundacion":"21641","nombreparrocopadre":"ARANDA TORRES CIRO ANTONIO","obispoiglesiaparroquia":"MONSEÑOR LUIS FELIPE SÁNCHEZ APONTE","diasatencionusuario":"LUNES; MARTES; MIÉRCOLES; JUEVES Y VIERNES","horariomisasentresemana":"DE LUNES A VIERNES A LAS 6:00 PM","horariomisasfindesemana":"SABADOS 6:00 PM Y DOMINGOS: 8:00 AM; 9:00 AM; 10:00 AM; 11:00 AM; 12:00 PM Y 6:00 PM","servcios":"BAUTIZOS; MISAS; MATRIMONIOS; PRIMERAS COMUNIONES; CONFIRMACIONES."},{"PartitionKey":"12b175c9-aae7-4f88-a3b9-a5930641d64f","RowKey":"442605c3-ea73-4e6e-95db-a7aacac1d1c9","nitparroquias":"820003478-5","nombreparroquialesia":"PARROQUIA DEL DIVINO NIÑO.","direccionparroquiaiglesia":"CARRERA 17 No 16 - 64","barrio":"20 DE JULIO","numerodetelefono_iglesia_parroquia":"3112561515","correoiglesiaparroquia":"parroquiadeldivinoniño@gmail.com","comunidad":"DIOCESANA","patrono":"EL DIVINO NIÑO","fechafundacion":"35993","nombreparrocopadre":"ALVARADO PÁEZ JOSÉ ANTONIO","obispoiglesiaparroquia":"MONSEÑOR LUIS FELIPE SÁNCHEZ APONTE","diasatencionusuario":"LUNES; MARTES; MIÉRCOLES; JUEVES Y VIERNES","horariomisasentresemana":"JUEVES 6:00 PM","horariomisasfindesemana":"DOMINGO 10:00 AM Y 6:00 PM","servcios":"BAUTIZOS; MISAS; MATRIMONIOS; PRIMERAS COMUNIONES; CONFIRMACIONES; PASTORAL JUVENIL."},{"PartitionKey":"a5c6dd33-84ce-4edd-89f1-bc94dc07bb87","RowKey":"f2ee3b91-2d69-4e1a-86ab-77e664c424f9","nitparroquias":"820005605-3","nombreparroquialesia":"PARROQUIA DEL ESPÍRITU SANTO.","direccionparroquiaiglesia":"CARRERA 6 No 28 - 56","barrio":"JARDIN DEL NORTE","numerodetelefono_iglesia_parroquia":"3112787628","correoiglesiaparroquia":"iesr39@yahoo.es","comunidad":"DIOCESANA","patrono":"ESPÍRITU SANTO","fechafundacion":"41368","nombreparrocopadre":"RABA SAAVEDRA ISMAEL ENRIQUE","obispoiglesiaparroquia":"MONSEÑOR LUIS FELIPE SÁNCHEZ APONTE","diasatencionusuario":"LUNES; MARTES; MIÉRCOLES; JUEVES Y VIERNES","horariomisasentresemana":"DE MARTES A JUEVES A LAS 6:00 PM Y VIERNES A LAS 5:00 PM","horariomisasfindesemana":"SABADO 6:00 PM Y DOMINGO A LAS 9:00 AM; 10:00 AM; 11:00 AM; 12:00 PM Y 6:00 PM","servcios":"BAUTIZOS; MISAS; MATRIMONIOS; PRIMERAS COMUNIONES; CONFIRMACIONES; CURSOS POR INTERNET PARA PRIMERA COMUNIÓN; CONFIRMACIÓN Y ORIENTACIÓN PARA FAMILIAS"},{"PartitionKey":"1704b545-dd45-4305-a461-9fd9e681662b","RowKey":"b3e37b3b-4dd2-4a72-a0bb-c150b927a965","nitparroquias":"820002034-4","nombreparroquialesia":"PARROQUIA DE MARÍA INMACULADA","direccionparroquiaiglesia":"CARRERA 3 No 9A - 56","barrio":"LA MAGDALENA","numerodetelefono_iglesia_parroquia":"3118922671","correoiglesiaparroquia":"curia@diocesisdechiquinquira.org","comunidad":"DIOCESANA","patrono":"MARÍA INMACULADA","fechafundacion":"35989","nombreparrocopadre":"CELY GUÍO ANTONIO","obispoiglesiaparroquia":"MONSEÑOR LUIS FELIPE SÁNCHEZ APONTE","diasatencionusuario":"LUNES; MARTES; MIÉRCOLES; JUEVES Y VIERNES","horariomisasentresemana":"MARTES 3:00 PM Y VIERNES 5:30 PM","horariomisasfindesemana":"SABADO 5:30 PM Y DOMINGO A LAS: 8:00 AM; 9:00 AM; 10:00 AM; 11:00 AM; 12:00 PM Y 6:00 PM","servcios":"BAUTIZOS; MISAS; MATRIMONIOS; PRIMERAS COMUNIONES; CONFIRMACIONES."},{"PartitionKey":"ffb437fc-761b-4d43-92c3-e0602aa2433a","RowKey":"4e7dbec6-b9a0-4152-8352-347054b7a699","nitparroquias":"891801865-4","nombreparroquialesia":"PARROQUIA DE LA SANTÍSIMA TRINIDAD.","direccionparroquiaiglesia":"CARRERA 9A No 5 -33","barrio":"BOYACA BAJO","numerodetelefono_iglesia_parroquia":"057-7263534","correoiglesiaparroquia":"santisimatrinidad@diocesisdechiquinquira.org","comunidad":"DIOCESANA","patrono":"SANTÍSIMA TRINIDAD","fechafundacion":"29690","nombreparrocopadre":"MONSEÑOR FORERO CASTILLO JUAN NORBERTO","obispoiglesiaparroquia":"MONSEÑOR LUIS FELIPE SÁNCHEZ APONTE","diasatencionusuario":"LUNES; MARTES; MIÉRCOLES; JUEVES Y VIERNES","horariomisasentresemana":"DE LUNES A VIERNES A LAS 6:00 PM","horariomisasfindesemana":"SABADO A LAS: 6:00 PM ; LOS DOMINGOS A LAS 8:00 AM; 9:00 AM; 10:00 AM; 11:00 AM; 12:00 PM Y 5:00 PM Y 6:00 PM","servcios":"BAUTIZOS; MISAS; MATRIMONIOS; PRIMERAS COMUNIONES; CONFIRMACIONES."},{"PartitionKey":"1aa70978-ceb1-4d96-bd82-ebed0e54f51b","RowKey":"36fe15e0-34c8-44e9-a391-d294114e4c8b","nitparroquias":"891800609-0","nombreparroquialesia":"PARROQUIA DE NUESTRA SEÑORA DE LA RENOVACIÓN","direccionparroquiaiglesia":"CARRERA 8 No 16 - 28","barrio":"CENTRO","numerodetelefono_iglesia_parroquia":"057-7262214","correoiglesiaparroquia":"parroquialarenovacion@hotmail.com","comunidad":"DOMINICA","patrono":"VIRGEN DE CHIQUINQUIRÁ","fechafundacion":"26/12/1586","nombreparrocopadre":"BARÓN SÁENZ JOSÉ SALOMÓN","obispoiglesiaparroquia":"MONSEÑOR LUIS FELIPE SÁNCHEZ APONTE","diasatencionusuario":"LUNES; MARTES; MIÉRCOLES; JUEVES Y VIERNES","horariomisasentresemana":"DE LUNES A VIERNES A LAS 7:00 AM Y A LAS 6:30 PM","horariomisasfindesemana":"SABADOS 6:00 AM; 7:00PM; 8:00 AM; 9:00 AM; 10:00 AM; 11:00 AM; 12:00 PM Y LOS DOMINGOS DE 7:00PM; 8:00 AM; 9:00 AM; 10:00 AM; 11:00 AM; 6:00 PM Y 7:00 PM","servcios":"BAUTIZOS; MISAS; MATRIMONIOS; PRIMERAS COMUNIONES; CONFIRMACIONES."}]}