{"d":[{"PartitionKey":"e0da3447-c70b-488e-a32d-f405e31f7aab","RowKey":"c839ede7-1dcc-4a1e-a444-f2bc24b1c56c","coddane":"115600000014","nit":"820001451-8","nominstedu":"Concentración Urbana San Antonio","nomrector":"Faustino Aguirre Cruz","email":"raquira_colsanantonio@sedboyaca.gov.co","numestu":"312","nomsede":"Concentración Urbana San Antonio","respsede":"Faustino Aguirre Cruz","direcsede":"Cra 3a No 4-89","zona":"Urbana","jornada":"Mañana","grados":"Transicion a quinto","niveles":"Primaria","metodologia":"Academica"},{"PartitionKey":"9cd9774a-0ef9-417a-873b-3993ae992a99","RowKey":"5d28d778-093f-4e92-b7fa-13891257081c","coddane":"115600000226","nit":"820001451-8","nominstedu":"Concentración Urbana San Antonio","nomrector":"Faustino Aguirre Cruz","email":"raquira_colsanantonio@sedboyaca.gov.co","numestu":"344","nomsede":"Colegio El Sol","respsede":"Faustino Aguirre Cruz","direcsede":"Cra 3a No 6-120","zona":"Urbana","jornada":"Mañana","grados":"Sexto a once","niveles":"Secundaria","metodologia":"Académica"},{"PartitionKey":"7c98def4-9597-4006-bcd9-48c9cc08b942","RowKey":"83165c66-abf1-4b32-bf53-60200f096655","coddane":"215600000302","nit":"820001451-8","nominstedu":"Concentración Urbana San Antonio","nomrector":"Faustino Aguirre Cruz","email":"raquira_colsanantonio@sedboyaca.gov.co","numestu":"61","nomsede":"Resguardo Occidente","respsede":"Julia Leal","direcsede":"Vereda Resguardo Occidente","zona":"Rural","jornada":"Mañana","grados":"Transicion a quinto","niveles":"Primaria","metodologia":"Escuela Nueva"},{"PartitionKey":"3b14eaaf-0713-401e-888a-c31636b9928e","RowKey":"fb8ae89c-73fa-414b-a31d-f7624e6ce2b1","coddane":"215600000116","nit":"820001451-8","nominstedu":"Concentración Urbana San Antonio","nomrector":"Faustino Aguirre Cruz","email":"raquira_colsanantonio@sedboyaca.gov.co","numestu":"9","nomsede":"Pueblo Viejo","respsede":"Genoveva Munevar","direcsede":"Vereda Pueblo Viejo","zona":"Rural","jornada":"Mañana","grados":"Transicion a quinto","niveles":"Primaria","metodologia":"Escuela Nueva"},{"PartitionKey":"fb44169a-3634-4e16-b4ce-fd7fd06d138f","RowKey":"30f4c9f1-c730-47bf-941a-07dd455fe1c7","coddane":"215600000043","nit":"820001451-8","nominstedu":"Concentración Urbana San Antonio","nomrector":"Faustino Aguirre Cruz","email":"raquira_colsanantonio@sedboyaca.gov.co","numestu":"46","nomsede":"Torres de San Pedro","respsede":"Doris Hernandez","direcsede":"Vereda Torres de San Pedro","zona":"Rural","jornada":"Mañana","grados":"Transicion a quinto","niveles":"Primaria","metodologia":"Escuela Nueva"},{"PartitionKey":"d4309f04-0681-4b81-8511-3f9d23159714","RowKey":"a60a3fbb-3d95-4525-956e-7785b64e6385","coddane":"215600000159","nit":"820001451-8","nominstedu":"Concentración Urbana San Antonio","nomrector":"Faustino Aguirre Cruz","email":"raquira_colsanantonio@sedboyaca.gov.co","numestu":"36","nomsede":"Quicagota","respsede":"Mareln Moreno","direcsede":"Verada Quicagota","zona":"Rural","jornada":"Mañana","grados":"Transicion a quinto","niveles":"Primaria","metodologia":"Escuela Nueva"},{"PartitionKey":"21fc27f7-7e5b-4225-88b8-859573ae01d0","RowKey":"6a1bdebe-1d35-490c-abfe-9033abef5685","coddane":"215600000094","nit":"820001451-8","nominstedu":"Concentración Urbana San Antonio","nomrector":"Faustino Aguirre Cruz","email":"raquira_colsanantonio@sedboyaca.gov.co","numestu":"14","nomsede":"Ollerias","respsede":"Nairo Molina","direcsede":"Vereda  Ollerias","zona":"Rural","jornada":"Mañana","grados":"Transicion a quinto","niveles":"Primaria","metodologia":"Escuela Nueva"},{"PartitionKey":"ebd27646-4899-4e7f-83a4-3d3346db0676","RowKey":"b354a529-d4cf-49d8-9044-d71bea70a368","coddane":"215600000027","nit":"820001451-8","nominstedu":"Concentración Urbana San Antonio","nomrector":"Faustino Aguirre Cruz","email":"raquira_colsanantonio@sedboyaca.gov.co","numestu":"12","nomsede":"San Cayetano","respsede":"Nelson Salgado","direcsede":"Vereda San Cayetano","zona":"Rural","jornada":"Mañana","grados":"Transicion a quinto","niveles":"Primaria","metodologia":"Escuela Nueva"},{"PartitionKey":"84b43b06-de8f-4908-ae75-fd206a61581b","RowKey":"cbd15b8e-1eaa-4b4b-807f-346572aed283","coddane":"215600000060","nit":"820001451-8","nominstedu":"Concentración Urbana San Antonio","nomrector":"Faustino Aguirre Cruz","email":"raquira_colsanantonio@sedboyaca.gov.co","numestu":"9","nomsede":"Mirque","respsede":"Angelica Sanchez","direcsede":"Vereda Mirque","zona":"Rural","jornada":"Mañana","grados":"Transicion a quinto","niveles":"Primaria","metodologia":"Escuela Nueva"}]}